[
  {
    "date": "01/20",
    "open": 2643.0,
    "high": 2715.0,
    "low": 2628.0,
    "close": 2674.0,
    "volume": 1001640
  },
  {
    "date": "01/21",
    "open": 2609.0,
    "high": 2649.0,
    "low": 2590.0,
    "close": 2621.0,
    "volume": 1223602
  },
  {
    "date": "01/22",
    "open": 2671.0,
    "high": 2718.0,
    "low": 2649.0,
    "close": 2660.0,
    "volume": 467306
  },
  {
    "date": "01/23",
    "open": 2610.0,
    "high": 2655.0,
    "low": 2579.0,
    "close": 2602.0,
    "volume": 1567818
  },
  {
    "date": "01/24",
    "open": 2716.0,
    "high": 2754.0,
    "low": 2677.0,
    "close": 2707.0,
    "volume": 1172400
  },
  {
    "date": "01/27",
    "open": 2692.0,
    "high": 2741.0,
    "low": 2658.0,
    "close": 2664.0,
    "volume": 1455964
  },
  {
    "date": "01/28",
    "open": 2552.0,
    "high": 2659.0,
    "low": 2519.0,
    "close": 2639.0,
    "volume": 562708
  },
  {
    "date": "01/29",
    "open": 2496.0,
    "high": 2530.0,
    "low": 2457.0,
    "close": 2520.0,
    "volume": 319773
  },
  {
    "date": "01/30",
    "open": 2512.0,
    "high": 2571.0,
    "low": 2492.0,
    "close": 2527.0,
    "volume": 381713
  },
  {
    "date": "01/31",
    "open": 2456.0,
    "high": 2525.0,
    "low": 2424.0,
    "close": 2495.0,
    "volume": 1244069
  },
  {
    "date": "02/03",
    "open": 2458.0,
    "high": 2462.0,
    "low": 2391.0,
    "close": 2405.0,
    "volume": 1632551
  },
  {
    "date": "02/04",
    "open": 2464.0,
    "high": 2504.0,
    "low": 2463.0,
    "close": 2498.0,
    "volume": 1775401
  },
  {
    "date": "02/05",
    "open": 2596.0,
    "high": 2615.0,
    "low": 2582.0,
    "close": 2584.0,
    "volume": 53663
  },
  {
    "date": "02/06",
    "open": 2530.0,
    "high": 2546.0,
    "low": 2415.0,
    "close": 2460.0,
    "volume": 501187
  },
  {
    "date": "02/07",
    "open": 2482.0,
    "high": 2502.0,
    "low": 2452.0,
    "close": 2457.0,
    "volume": 459992
  },
  {
    "date": "02/10",
    "open": 2380.0,
    "high": 2417.0,
    "low": 2343.0,
    "close": 2395.0,
    "volume": 985301
  },
  {
    "date": "02/11",
    "open": 2420.0,
    "high": 2440.0,
    "low": 2394.0,
    "close": 2401.0,
    "volume": 1041842
  },
  {
    "date": "02/12",
    "open": 2357.0,
    "high": 2383.0,
    "low": 2283.0,
    "close": 2319.0,
    "volume": 275714
  },
  {
    "date": "02/13",
    "open": 2302.0,
    "high": 2357.0,
    "low": 2299.0,
    "close": 2328.0,
    "volume": 1980655
  },
  {
    "date": "02/14",
    "open": 2422.0,
    "high": 2450.0,
    "low": 2367.0,
    "close": 2389.0,
    "volume": 554438
  },
  {
    "date": "02/17",
    "open": 2429.0,
    "high": 2443.0,
    "low": 2371.0,
    "close": 2383.0,
    "volume": 1153888
  },
  {
    "date": "02/18",
    "open": 2369.0,
    "high": 2376.0,
    "low": 2304.0,
    "close": 2342.0,
    "volume": 693313
  },
  {
    "date": "02/19",
    "open": 2351.0,
    "high": 2422.0,
    "low": 2331.0,
    "close": 2391.0,
    "volume": 1014641
  },
  {
    "date": "02/20",
    "open": 2436.0,
    "high": 2480.0,
    "low": 2353.0,
    "close": 2380.0,
    "volume": 1101925
  },
  {
    "date": "02/21",
    "open": 2440.0,
    "high": 2488.0,
    "low": 2420.0,
    "close": 2483.0,
    "volume": 723283
  },
  {
    "date": "02/24",
    "open": 2517.0,
    "high": 2546.0,
    "low": 2452.0,
    "close": 2487.0,
    "volume": 1011678
  },
  {
    "date": "02/25",
    "open": 2638.0,
    "high": 2673.0,
    "low": 2562.0,
    "close": 2588.0,
    "volume": 1345282
  },
  {
    "date": "02/26",
    "open": 2610.0,
    "high": 2649.0,
    "low": 2597.0,
    "close": 2602.0,
    "volume": 1205266
  },
  {
    "date": "02/27",
    "open": 2510.0,
    "high": 2562.0,
    "low": 2499.0,
    "close": 2543.0,
    "volume": 1475185
  },
  {
    "date": "02/28",
    "open": 2613.0,
    "high": 2616.0,
    "low": 2560.0,
    "close": 2600.0,
    "volume": 870944
  },
  {
    "date": "03/03",
    "open": 2603.0,
    "high": 2631.0,
    "low": 2513.0,
    "close": 2559.0,
    "volume": 1937617
  },
  {
    "date": "03/04",
    "open": 2683.0,
    "high": 2730.0,
    "low": 2661.0,
    "close": 2679.0,
    "volume": 1497994
  },
  {
    "date": "03/05",
    "open": 2642.0,
    "high": 2667.0,
    "low": 2613.0,
    "close": 2616.0,
    "volume": 84878
  },
  {
    "date": "03/06",
    "open": 2630.0,
    "high": 2666.0,
    "low": 2590.0,
    "close": 2614.0,
    "volume": 1106390
  },
  {
    "date": "03/07",
    "open": 2673.0,
    "high": 2711.0,
    "low": 2564.0,
    "close": 2583.0,
    "volume": 70516
  },
  {
    "date": "03/10",
    "open": 2673.0,
    "high": 2690.0,
    "low": 2638.0,
    "close": 2648.0,
    "volume": 1750865
  },
  {
    "date": "03/11",
    "open": 2756.0,
    "high": 2779.0,
    "low": 2730.0,
    "close": 2746.0,
    "volume": 907729
  },
  {
    "date": "03/12",
    "open": 2699.0,
    "high": 2727.0,
    "low": 2638.0,
    "close": 2651.0,
    "volume": 280619
  },
  {
    "date": "03/13",
    "open": 2722.0,
    "high": 2757.0,
    "low": 2648.0,
    "close": 2692.0,
    "volume": 1268056
  },
  {
    "date": "03/14",
    "open": 2779.0,
    "high": 2814.0,
    "low": 2741.0,
    "close": 2752.0,
    "volume": 1581538
  },
  {
    "date": "03/17",
    "open": 2843.0,
    "high": 2882.0,
    "low": 2796.0,
    "close": 2825.0,
    "volume": 646782
  },
  {
    "date": "03/18",
    "open": 2777.0,
    "high": 2857.0,
    "low": 2754.0,
    "close": 2806.0,
    "volume": 598566
  },
  {
    "date": "03/19",
    "open": 2829.0,
    "high": 2883.0,
    "low": 2737.0,
    "close": 2778.0,
    "volume": 1828137
  },
  {
    "date": "03/20",
    "open": 2779.0,
    "high": 2919.0,
    "low": 2749.0,
    "close": 2884.0,
    "volume": 1317790
  },
  {
    "date": "03/21",
    "open": 2787.0,
    "high": 2850.0,
    "low": 2756.0,
    "close": 2811.0,
    "volume": 1298133
  },
  {
    "date": "03/24",
    "open": 2840.0,
    "high": 2840.0,
    "low": 2730.0,
    "close": 2781.0,
    "volume": 732869
  },
  {
    "date": "03/25",
    "open": 2776.0,
    "high": 2787.0,
    "low": 2700.0,
    "close": 2742.0,
    "volume": 1579638
  },
  {
    "date": "03/26",
    "open": 2809.0,
    "high": 2843.0,
    "low": 2793.0,
    "close": 2832.0,
    "volume": 569621
  },
  {
    "date": "03/27",
    "open": 2925.0,
    "high": 2935.0,
    "low": 2840.0,
    "close": 2866.0,
    "volume": 990761
  },
  {
    "date": "03/28",
    "open": 2810.0,
    "high": 2843.0,
    "low": 2761.0,
    "close": 2821.0,
    "volume": 1583786
  },
  {
    "date": "03/31",
    "open": 2847.0,
    "high": 2879.0,
    "low": 2807.0,
    "close": 2820.0,
    "volume": 1739653
  },
  {
    "date": "04/01",
    "open": 2803.0,
    "high": 2829.0,
    "low": 2757.0,
    "close": 2828.0,
    "volume": 516856
  },
  {
    "date": "04/02",
    "open": 2707.0,
    "high": 2754.0,
    "low": 2658.0,
    "close": 2752.0,
    "volume": 372847
  },
  {
    "date": "04/03",
    "open": 2783.0,
    "high": 2793.0,
    "low": 2738.0,
    "close": 2754.0,
    "volume": 291144
  },
  {
    "date": "04/04",
    "open": 2769.0,
    "high": 2801.0,
    "low": 2688.0,
    "close": 2718.0,
    "volume": 1712296
  },
  {
    "date": "04/07",
    "open": 2773.0,
    "high": 2785.0,
    "low": 2675.0,
    "close": 2718.0,
    "volume": 311298
  },
  {
    "date": "04/08",
    "open": 2792.0,
    "high": 2869.0,
    "low": 2759.0,
    "close": 2840.0,
    "volume": 643281
  },
  {
    "date": "04/09",
    "open": 2858.0,
    "high": 2868.0,
    "low": 2831.0,
    "close": 2863.0,
    "volume": 501294
  },
  {
    "date": "04/10",
    "open": 2790.0,
    "high": 2878.0,
    "low": 2770.0,
    "close": 2845.0,
    "volume": 992988
  },
  {
    "date": "04/11",
    "open": 2824.0,
    "high": 2825.0,
    "low": 2775.0,
    "close": 2802.0,
    "volume": 1238571
  },
  {
    "date": "04/14",
    "open": 2847.0,
    "high": 2931.0,
    "low": 2843.0,
    "close": 2875.0,
    "volume": 207270
  },
  {
    "date": "04/15",
    "open": 2816.0,
    "high": 2906.0,
    "low": 2777.0,
    "close": 2888.0,
    "volume": 757860
  },
  {
    "date": "04/16",
    "open": 2797.0,
    "high": 2901.0,
    "low": 2742.0,
    "close": 2879.0,
    "volume": 564697
  },
  {
    "date": "04/17",
    "open": 2796.0,
    "high": 2819.0,
    "low": 2736.0,
    "close": 2785.0,
    "volume": 1191917
  },
  {
    "date": "04/18",
    "open": 2674.0,
    "high": 2738.0,
    "low": 2631.0,
    "close": 2687.0,
    "volume": 1246776
  },
  {
    "date": "04/21",
    "open": 2680.0,
    "high": 2789.0,
    "low": 2638.0,
    "close": 2779.0,
    "volume": 1702916
  },
  {
    "date": "04/22",
    "open": 2819.0,
    "high": 2872.0,
    "low": 2779.0,
    "close": 2835.0,
    "volume": 941287
  },
  {
    "date": "04/23",
    "open": 2777.0,
    "high": 2853.0,
    "low": 2772.0,
    "close": 2847.0,
    "volume": 193341
  },
  {
    "date": "04/24",
    "open": 2921.0,
    "high": 2935.0,
    "low": 2776.0,
    "close": 2823.0,
    "volume": 336326
  },
  {
    "date": "04/25",
    "open": 2923.0,
    "high": 2986.0,
    "low": 2898.0,
    "close": 2937.0,
    "volume": 310400
  },
  {
    "date": "04/28",
    "open": 2951.0,
    "high": 2978.0,
    "low": 2859.0,
    "close": 2884.0,
    "volume": 1166728
  },
  {
    "date": "04/29",
    "open": 2825.0,
    "high": 2873.0,
    "low": 2772.0,
    "close": 2821.0,
    "volume": 220981
  },
  {
    "date": "04/30",
    "open": 2809.0,
    "high": 2827.0,
    "low": 2743.0,
    "close": 2763.0,
    "volume": 113422
  },
  {
    "date": "05/01",
    "open": 2862.0,
    "high": 2906.0,
    "low": 2811.0,
    "close": 2871.0,
    "volume": 1288531
  },
  {
    "date": "05/02",
    "open": 2783.0,
    "high": 2824.0,
    "low": 2779.0,
    "close": 2820.0,
    "volume": 1990860
  },
  {
    "date": "05/05",
    "open": 2710.0,
    "high": 2743.0,
    "low": 2690.0,
    "close": 2721.0,
    "volume": 1477225
  },
  {
    "date": "05/06",
    "open": 2735.0,
    "high": 2809.0,
    "low": 2722.0,
    "close": 2782.0,
    "volume": 1380223
  },
  {
    "date": "05/07",
    "open": 2724.0,
    "high": 2775.0,
    "low": 2679.0,
    "close": 2691.0,
    "volume": 1664985
  },
  {
    "date": "05/08",
    "open": 2780.0,
    "high": 2799.0,
    "low": 2715.0,
    "close": 2768.0,
    "volume": 1762813
  },
  {
    "date": "05/09",
    "open": 2739.0,
    "high": 2780.0,
    "low": 2693.0,
    "close": 2769.0,
    "volume": 332645
  },
  {
    "date": "05/12",
    "open": 2827.0,
    "high": 2829.0,
    "low": 2787.0,
    "close": 2827.0,
    "volume": 913668
  },
  {
    "date": "05/13",
    "open": 2789.0,
    "high": 2792.0,
    "low": 2731.0,
    "close": 2775.0,
    "volume": 1799739
  },
  {
    "date": "05/14",
    "open": 2782.0,
    "high": 2880.0,
    "low": 2778.0,
    "close": 2853.0,
    "volume": 1164217
  },
  {
    "date": "05/15",
    "open": 2770.0,
    "high": 2815.0,
    "low": 2725.0,
    "close": 2771.0,
    "volume": 1799856
  },
  {
    "date": "05/16",
    "open": 2718.0,
    "high": 2790.0,
    "low": 2677.0,
    "close": 2762.0,
    "volume": 1311950
  },
  {
    "date": "05/19",
    "open": 2660.0,
    "high": 2742.0,
    "low": 2636.0,
    "close": 2725.0,
    "volume": 993362
  },
  {
    "date": "05/20",
    "open": 2765.0,
    "high": 2820.0,
    "low": 2764.0,
    "close": 2766.0,
    "volume": 943804
  },
  {
    "date": "05/21",
    "open": 2813.0,
    "high": 2851.0,
    "low": 2794.0,
    "close": 2839.0,
    "volume": 840941
  },
  {
    "date": "05/22",
    "open": 2797.0,
    "high": 2839.0,
    "low": 2749.0,
    "close": 2828.0,
    "volume": 618621
  },
  {
    "date": "05/23",
    "open": 2860.0,
    "high": 2885.0,
    "low": 2852.0,
    "close": 2874.0,
    "volume": 1019341
  },
  {
    "date": "05/26",
    "open": 2903.0,
    "high": 2918.0,
    "low": 2823.0,
    "close": 2836.0,
    "volume": 1715809
  },
  {
    "date": "05/27",
    "open": 2854.0,
    "high": 2938.0,
    "low": 2828.0,
    "close": 2885.0,
    "volume": 941470
  },
  {
    "date": "05/28",
    "open": 2883.0,
    "high": 2940.0,
    "low": 2876.0,
    "close": 2908.0,
    "volume": 1125581
  },
  {
    "date": "05/29",
    "open": 2961.0,
    "high": 2983.0,
    "low": 2893.0,
    "close": 2940.0,
    "volume": 1282759
  },
  {
    "date": "05/30",
    "open": 2934.0,
    "high": 2968.0,
    "low": 2931.0,
    "close": 2933.0,
    "volume": 1980914
  },
  {
    "date": "06/02",
    "open": 2988.0,
    "high": 3036.0,
    "low": 2854.0,
    "close": 2910.0,
    "volume": 228599
  },
  {
    "date": "06/03",
    "open": 2971.0,
    "high": 3038.0,
    "low": 2940.0,
    "close": 2993.0,
    "volume": 719412
  },
  {
    "date": "06/04",
    "open": 3015.0,
    "high": 3068.0,
    "low": 3000.0,
    "close": 3052.0,
    "volume": 321020
  },
  {
    "date": "06/05",
    "open": 2967.0,
    "high": 3099.0,
    "low": 2918.0,
    "close": 3059.0,
    "volume": 1471162
  },
  {
    "date": "06/06",
    "open": 2882.0,
    "high": 2947.0,
    "low": 2826.0,
    "close": 2937.0,
    "volume": 1777013
  },
  {
    "date": "06/09",
    "open": 2899.0,
    "high": 2938.0,
    "low": 2843.0,
    "close": 2873.0,
    "volume": 673014
  },
  {
    "date": "06/10",
    "open": 2862.0,
    "high": 2883.0,
    "low": 2839.0,
    "close": 2872.0,
    "volume": 1141845
  },
  {
    "date": "06/11",
    "open": 2863.0,
    "high": 2885.0,
    "low": 2820.0,
    "close": 2835.0,
    "volume": 947901
  },
  {
    "date": "06/12",
    "open": 3021.0,
    "high": 3066.0,
    "low": 2955.0,
    "close": 2966.0,
    "volume": 1112918
  },
  {
    "date": "06/13",
    "open": 2888.0,
    "high": 2945.0,
    "low": 2858.0,
    "close": 2927.0,
    "volume": 1369709
  },
  {
    "date": "06/16",
    "open": 2987.0,
    "high": 3018.0,
    "low": 2904.0,
    "close": 2952.0,
    "volume": 1013020
  },
  {
    "date": "06/17",
    "open": 2970.0,
    "high": 3070.0,
    "low": 2939.0,
    "close": 3030.0,
    "volume": 1386819
  },
  {
    "date": "06/18",
    "open": 3071.0,
    "high": 3117.0,
    "low": 2977.0,
    "close": 2993.0,
    "volume": 1705326
  },
  {
    "date": "06/19",
    "open": 3008.0,
    "high": 3027.0,
    "low": 2935.0,
    "close": 2989.0,
    "volume": 1843801
  },
  {
    "date": "06/20",
    "open": 3007.0,
    "high": 3081.0,
    "low": 2997.0,
    "close": 3076.0,
    "volume": 720136
  },
  {
    "date": "06/23",
    "open": 3049.0,
    "high": 3086.0,
    "low": 3021.0,
    "close": 3056.0,
    "volume": 776727
  },
  {
    "date": "06/24",
    "open": 3052.0,
    "high": 3088.0,
    "low": 2964.0,
    "close": 3008.0,
    "volume": 1889591
  },
  {
    "date": "06/25",
    "open": 2974.0,
    "high": 3029.0,
    "low": 2963.0,
    "close": 2979.0,
    "volume": 105238
  },
  {
    "date": "06/26",
    "open": 3039.0,
    "high": 3068.0,
    "low": 2963.0,
    "close": 2973.0,
    "volume": 1545138
  },
  {
    "date": "06/27",
    "open": 3060.0,
    "high": 3138.0,
    "low": 3028.0,
    "close": 3095.0,
    "volume": 1838207
  },
  {
    "date": "06/30",
    "open": 3038.0,
    "high": 3097.0,
    "low": 2969.0,
    "close": 3007.0,
    "volume": 527826
  },
  {
    "date": "07/01",
    "open": 3135.0,
    "high": 3192.0,
    "low": 3078.0,
    "close": 3095.0,
    "volume": 1716366
  },
  {
    "date": "07/02",
    "open": 3126.0,
    "high": 3162.0,
    "low": 3051.0,
    "close": 3111.0,
    "volume": 1216233
  },
  {
    "date": "07/03",
    "open": 3253.0,
    "high": 3286.0,
    "low": 3170.0,
    "close": 3223.0,
    "volume": 1408290
  },
  {
    "date": "07/04",
    "open": 3103.0,
    "high": 3139.0,
    "low": 3076.0,
    "close": 3135.0,
    "volume": 313552
  },
  {
    "date": "07/07",
    "open": 3090.0,
    "high": 3119.0,
    "low": 3066.0,
    "close": 3075.0,
    "volume": 760050
  },
  {
    "date": "07/08",
    "open": 3114.0,
    "high": 3192.0,
    "low": 3109.0,
    "close": 3131.0,
    "volume": 1283456
  },
  {
    "date": "07/09",
    "open": 3204.0,
    "high": 3258.0,
    "low": 3147.0,
    "close": 3188.0,
    "volume": 590167
  },
  {
    "date": "07/10",
    "open": 3174.0,
    "high": 3224.0,
    "low": 3134.0,
    "close": 3146.0,
    "volume": 1676178
  },
  {
    "date": "07/11",
    "open": 3177.0,
    "high": 3255.0,
    "low": 3143.0,
    "close": 3199.0,
    "volume": 1317919
  },
  {
    "date": "07/14",
    "open": 3240.0,
    "high": 3274.0,
    "low": 3188.0,
    "close": 3188.0,
    "volume": 859552
  },
  {
    "date": "07/15",
    "open": 3319.0,
    "high": 3385.0,
    "low": 3191.0,
    "close": 3228.0,
    "volume": 710196
  },
  {
    "date": "07/16",
    "open": 3255.0,
    "high": 3280.0,
    "low": 3168.0,
    "close": 3170.0,
    "volume": 1974140
  },
  {
    "date": "07/17",
    "open": 3221.0,
    "high": 3275.0,
    "low": 3189.0,
    "close": 3202.0,
    "volume": 1872773
  },
  {
    "date": "07/18",
    "open": 3251.0,
    "high": 3265.0,
    "low": 3197.0,
    "close": 3255.0,
    "volume": 64364
  },
  {
    "date": "07/21",
    "open": 3386.0,
    "high": 3415.0,
    "low": 3335.0,
    "close": 3393.0,
    "volume": 187878
  },
  {
    "date": "07/22",
    "open": 3370.0,
    "high": 3446.0,
    "low": 3346.0,
    "close": 3419.0,
    "volume": 640763
  },
  {
    "date": "07/23",
    "open": 3295.0,
    "high": 3380.0,
    "low": 3236.0,
    "close": 3362.0,
    "volume": 422187
  },
  {
    "date": "07/24",
    "open": 3310.0,
    "high": 3352.0,
    "low": 3193.0,
    "close": 3247.0,
    "volume": 1060506
  },
  {
    "date": "07/25",
    "open": 3257.0,
    "high": 3276.0,
    "low": 3199.0,
    "close": 3240.0,
    "volume": 1828657
  },
  {
    "date": "07/28",
    "open": 3134.0,
    "high": 3156.0,
    "low": 3083.0,
    "close": 3146.0,
    "volume": 1360755
  },
  {
    "date": "07/29",
    "open": 3252.0,
    "high": 3308.0,
    "low": 3155.0,
    "close": 3186.0,
    "volume": 625654
  },
  {
    "date": "07/30",
    "open": 3190.0,
    "high": 3240.0,
    "low": 3135.0,
    "close": 3187.0,
    "volume": 413233
  },
  {
    "date": "07/31",
    "open": 3089.0,
    "high": 3156.0,
    "low": 3027.0,
    "close": 3098.0,
    "volume": 858893
  },
  {
    "date": "08/01",
    "open": 3238.0,
    "high": 3277.0,
    "low": 3149.0,
    "close": 3212.0,
    "volume": 1111676
  },
  {
    "date": "08/04",
    "open": 3293.0,
    "high": 3328.0,
    "low": 3211.0,
    "close": 3213.0,
    "volume": 1627767
  },
  {
    "date": "08/05",
    "open": 3268.0,
    "high": 3425.0,
    "low": 3230.0,
    "close": 3368.0,
    "volume": 779262
  },
  {
    "date": "08/06",
    "open": 3408.0,
    "high": 3425.0,
    "low": 3342.0,
    "close": 3372.0,
    "volume": 840625
  },
  {
    "date": "08/07",
    "open": 3341.0,
    "high": 3423.0,
    "low": 3275.0,
    "close": 3378.0,
    "volume": 1880755
  },
  {
    "date": "08/08",
    "open": 3475.0,
    "high": 3537.0,
    "low": 3379.0,
    "close": 3428.0,
    "volume": 1837184
  },
  {
    "date": "08/11",
    "open": 3441.0,
    "high": 3525.0,
    "low": 3388.0,
    "close": 3520.0,
    "volume": 1167013
  },
  {
    "date": "08/12",
    "open": 3385.0,
    "high": 3498.0,
    "low": 3360.0,
    "close": 3497.0,
    "volume": 447206
  },
  {
    "date": "08/13",
    "open": 3459.0,
    "high": 3471.0,
    "low": 3367.0,
    "close": 3414.0,
    "volume": 1014899
  },
  {
    "date": "08/14",
    "open": 3516.0,
    "high": 3575.0,
    "low": 3432.0,
    "close": 3444.0,
    "volume": 413111
  },
  {
    "date": "08/15",
    "open": 3450.0,
    "high": 3507.0,
    "low": 3422.0,
    "close": 3443.0,
    "volume": 1598980
  },
  {
    "date": "08/18",
    "open": 3516.0,
    "high": 3544.0,
    "low": 3473.0,
    "close": 3494.0,
    "volume": 1320831
  },
  {
    "date": "08/19",
    "open": 3669.0,
    "high": 3707.0,
    "low": 3553.0,
    "close": 3622.0,
    "volume": 1869380
  },
  {
    "date": "08/20",
    "open": 3470.0,
    "high": 3543.0,
    "low": 3456.0,
    "close": 3500.0,
    "volume": 1797505
  },
  {
    "date": "08/21",
    "open": 3533.0,
    "high": 3580.0,
    "low": 3428.0,
    "close": 3429.0,
    "volume": 1751733
  },
  {
    "date": "08/22",
    "open": 3494.0,
    "high": 3548.0,
    "low": 3362.0,
    "close": 3393.0,
    "volume": 1067026
  },
  {
    "date": "08/25",
    "open": 3394.0,
    "high": 3421.0,
    "low": 3279.0,
    "close": 3291.0,
    "volume": 1968844
  },
  {
    "date": "08/26",
    "open": 3354.0,
    "high": 3358.0,
    "low": 3335.0,
    "close": 3354.0,
    "volume": 183711
  },
  {
    "date": "08/27",
    "open": 3271.0,
    "high": 3273.0,
    "low": 3214.0,
    "close": 3247.0,
    "volume": 1843231
  },
  {
    "date": "08/28",
    "open": 3289.0,
    "high": 3380.0,
    "low": 3252.0,
    "close": 3349.0,
    "volume": 541694
  },
  {
    "date": "08/29",
    "open": 3284.0,
    "high": 3297.0,
    "low": 3181.0,
    "close": 3226.0,
    "volume": 1789278
  },
  {
    "date": "09/01",
    "open": 3211.0,
    "high": 3242.0,
    "low": 3164.0,
    "close": 3174.0,
    "volume": 1125528
  },
  {
    "date": "09/02",
    "open": 3272.0,
    "high": 3301.0,
    "low": 3148.0,
    "close": 3206.0,
    "volume": 82525
  },
  {
    "date": "09/03",
    "open": 3254.0,
    "high": 3316.0,
    "low": 3234.0,
    "close": 3295.0,
    "volume": 1965800
  },
  {
    "date": "09/04",
    "open": 3272.0,
    "high": 3398.0,
    "low": 3269.0,
    "close": 3333.0,
    "volume": 1054369
  },
  {
    "date": "09/05",
    "open": 3300.0,
    "high": 3318.0,
    "low": 3260.0,
    "close": 3298.0,
    "volume": 586470
  },
  {
    "date": "09/08",
    "open": 3323.0,
    "high": 3390.0,
    "low": 3312.0,
    "close": 3324.0,
    "volume": 1658443
  },
  {
    "date": "09/09",
    "open": 3148.0,
    "high": 3204.0,
    "low": 3116.0,
    "close": 3197.0,
    "volume": 956898
  },
  {
    "date": "09/10",
    "open": 3195.0,
    "high": 3291.0,
    "low": 3174.0,
    "close": 3236.0,
    "volume": 1220578
  },
  {
    "date": "09/11",
    "open": 3143.0,
    "high": 3197.0,
    "low": 3133.0,
    "close": 3147.0,
    "volume": 1974973
  },
  {
    "date": "09/12",
    "open": 3228.0,
    "high": 3274.0,
    "low": 3181.0,
    "close": 3270.0,
    "volume": 1753199
  },
  {
    "date": "09/15",
    "open": 3281.0,
    "high": 3387.0,
    "low": 3235.0,
    "close": 3328.0,
    "volume": 1445116
  },
  {
    "date": "09/16",
    "open": 3268.0,
    "high": 3324.0,
    "low": 3221.0,
    "close": 3296.0,
    "volume": 373075
  },
  {
    "date": "09/17",
    "open": 3197.0,
    "high": 3234.0,
    "low": 3140.0,
    "close": 3162.0,
    "volume": 421960
  },
  {
    "date": "09/18",
    "open": 3132.0,
    "high": 3166.0,
    "low": 3099.0,
    "close": 3134.0,
    "volume": 724995
  },
  {
    "date": "09/19",
    "open": 3069.0,
    "high": 3130.0,
    "low": 3034.0,
    "close": 3048.0,
    "volume": 1928720
  },
  {
    "date": "09/22",
    "open": 3029.0,
    "high": 3143.0,
    "low": 2978.0,
    "close": 3095.0,
    "volume": 97947
  },
  {
    "date": "09/23",
    "open": 3138.0,
    "high": 3184.0,
    "low": 3069.0,
    "close": 3094.0,
    "volume": 1579432
  },
  {
    "date": "09/24",
    "open": 3178.0,
    "high": 3227.0,
    "low": 3125.0,
    "close": 3139.0,
    "volume": 1477601
  }
]