[
  {
    "date": "01/20",
    "open": 1041.0,
    "high": 1048.0,
    "low": 1022.0,
    "close": 1043.0,
    "volume": 771932
  },
  {
    "date": "01/21",
    "open": 1033.0,
    "high": 1050.0,
    "low": 1017.0,
    "close": 1020.0,
    "volume": 507000
  },
  {
    "date": "01/22",
    "open": 985.0,
    "high": 990.0,
    "low": 970.0,
    "close": 982.0,
    "volume": 1169965
  },
  {
    "date": "01/23",
    "open": 1009.0,
    "high": 1027.0,
    "low": 968.0,
    "close": 981.0,
    "volume": 1162186
  },
  {
    "date": "01/24",
    "open": 974.0,
    "high": 995.0,
    "low": 965.0,
    "close": 978.0,
    "volume": 538799
  },
  {
    "date": "01/27",
    "open": 999.0,
    "high": 1014.0,
    "low": 960.0,
    "close": 964.0,
    "volume": 1587439
  },
  {
    "date": "01/28",
    "open": 986.0,
    "high": 987.0,
    "low": 974.0,
    "close": 981.0,
    "volume": 1349628
  },
  {
    "date": "01/29",
    "open": 979.0,
    "high": 992.0,
    "low": 977.0,
    "close": 989.0,
    "volume": 1362752
  },
  {
    "date": "01/30",
    "open": 941.0,
    "high": 990.0,
    "low": 929.0,
    "close": 976.0,
    "volume": 1520811
  },
  {
    "date": "01/31",
    "open": 929.0,
    "high": 945.0,
    "low": 911.0,
    "close": 938.0,
    "volume": 1062141
  },
  {
    "date": "02/03",
    "open": 935.0,
    "high": 953.0,
    "low": 916.0,
    "close": 917.0,
    "volume": 1026283
  },
  {
    "date": "02/04",
    "open": 957.0,
    "high": 970.0,
    "low": 929.0,
    "close": 931.0,
    "volume": 1095440
  },
  {
    "date": "02/05",
    "open": 942.0,
    "high": 958.0,
    "low": 901.0,
    "close": 911.0,
    "volume": 568683
  },
  {
    "date": "02/06",
    "open": 926.0,
    "high": 944.0,
    "low": 890.0,
    "close": 905.0,
    "volume": 366001
  },
  {
    "date": "02/07",
    "open": 920.0,
    "high": 958.0,
    "low": 903.0,
    "close": 940.0,
    "volume": 1897001
  },
  {
    "date": "02/10",
    "open": 931.0,
    "high": 966.0,
    "low": 928.0,
    "close": 949.0,
    "volume": 1869338
  },
  {
    "date": "02/11",
    "open": 959.0,
    "high": 972.0,
    "low": 953.0,
    "close": 968.0,
    "volume": 856609
  },
  {
    "date": "02/12",
    "open": 981.0,
    "high": 994.0,
    "low": 955.0,
    "close": 970.0,
    "volume": 565156
  },
  {
    "date": "02/13",
    "open": 939.0,
    "high": 960.0,
    "low": 932.0,
    "close": 953.0,
    "volume": 1871603
  },
  {
    "date": "02/14",
    "open": 975.0,
    "high": 983.0,
    "low": 948.0,
    "close": 955.0,
    "volume": 1451437
  },
  {
    "date": "02/17",
    "open": 959.0,
    "high": 979.0,
    "low": 955.0,
    "close": 960.0,
    "volume": 1012410
  },
  {
    "date": "02/18",
    "open": 961.0,
    "high": 977.0,
    "low": 921.0,
    "close": 935.0,
    "volume": 558942
  },
  {
    "date": "02/19",
    "open": 951.0,
    "high": 962.0,
    "low": 904.0,
    "close": 919.0,
    "volume": 1367276
  },
  {
    "date": "02/20",
    "open": 970.0,
    "high": 991.0,
    "low": 967.0,
    "close": 976.0,
    "volume": 1196051
  },
  {
    "date": "02/21",
    "open": 941.0,
    "high": 960.0,
    "low": 937.0,
    "close": 955.0,
    "volume": 228689
  },
  {
    "date": "02/24",
    "open": 954.0,
    "high": 995.0,
    "low": 942.0,
    "close": 978.0,
    "volume": 956929
  },
  {
    "date": "02/25",
    "open": 945.0,
    "high": 959.0,
    "low": 918.0,
    "close": 933.0,
    "volume": 1839455
  },
  {
    "date": "02/26",
    "open": 935.0,
    "high": 952.0,
    "low": 929.0,
    "close": 940.0,
    "volume": 1232765
  },
  {
    "date": "02/27",
    "open": 968.0,
    "high": 974.0,
    "low": 957.0,
    "close": 958.0,
    "volume": 802578
  },
  {
    "date": "02/28",
    "open": 958.0,
    "high": 971.0,
    "low": 944.0,
    "close": 954.0,
    "volume": 1301445
  },
  {
    "date": "03/03",
    "open": 995.0,
    "high": 1017.0,
    "low": 981.0,
    "close": 1002.0,
    "volume": 581518
  },
  {
    "date": "03/04",
    "open": 984.0,
    "high": 999.0,
    "low": 979.0,
    "close": 994.0,
    "volume": 370397
  },
  {
    "date": "03/05",
    "open": 1013.0,
    "high": 1029.0,
    "low": 991.0,
    "close": 1011.0,
    "volume": 1711547
  },
  {
    "date": "03/06",
    "open": 992.0,
    "high": 1012.0,
    "low": 984.0,
    "close": 1003.0,
    "volume": 445939
  },
  {
    "date": "03/07",
    "open": 947.0,
    "high": 951.0,
    "low": 930.0,
    "close": 949.0,
    "volume": 553835
  },
  {
    "date": "03/10",
    "open": 956.0,
    "high": 966.0,
    "low": 950.0,
    "close": 964.0,
    "volume": 1237825
  },
  {
    "date": "03/11",
    "open": 1000.0,
    "high": 1012.0,
    "low": 972.0,
    "close": 976.0,
    "volume": 1469511
  },
  {
    "date": "03/12",
    "open": 957.0,
    "high": 989.0,
    "low": 951.0,
    "close": 977.0,
    "volume": 985061
  },
  {
    "date": "03/13",
    "open": 980.0,
    "high": 994.0,
    "low": 971.0,
    "close": 972.0,
    "volume": 1905152
  },
  {
    "date": "03/14",
    "open": 964.0,
    "high": 980.0,
    "low": 958.0,
    "close": 975.0,
    "volume": 1889561
  },
  {
    "date": "03/17",
    "open": 980.0,
    "high": 990.0,
    "low": 969.0,
    "close": 971.0,
    "volume": 1660216
  },
  {
    "date": "03/18",
    "open": 961.0,
    "high": 976.0,
    "low": 918.0,
    "close": 930.0,
    "volume": 1949722
  },
  {
    "date": "03/19",
    "open": 969.0,
    "high": 990.0,
    "low": 967.0,
    "close": 985.0,
    "volume": 787979
  },
  {
    "date": "03/20",
    "open": 985.0,
    "high": 987.0,
    "low": 968.0,
    "close": 977.0,
    "volume": 494640
  },
  {
    "date": "03/21",
    "open": 973.0,
    "high": 976.0,
    "low": 957.0,
    "close": 969.0,
    "volume": 710402
  },
  {
    "date": "03/24",
    "open": 996.0,
    "high": 1013.0,
    "low": 952.0,
    "close": 969.0,
    "volume": 1083177
  },
  {
    "date": "03/25",
    "open": 952.0,
    "high": 988.0,
    "low": 936.0,
    "close": 973.0,
    "volume": 340397
  },
  {
    "date": "03/26",
    "open": 983.0,
    "high": 986.0,
    "low": 969.0,
    "close": 985.0,
    "volume": 950963
  },
  {
    "date": "03/27",
    "open": 1003.0,
    "high": 1011.0,
    "low": 990.0,
    "close": 1000.0,
    "volume": 1883220
  },
  {
    "date": "03/28",
    "open": 1019.0,
    "high": 1039.0,
    "low": 1008.0,
    "close": 1033.0,
    "volume": 1457729
  },
  {
    "date": "03/31",
    "open": 1034.0,
    "high": 1039.0,
    "low": 1005.0,
    "close": 1014.0,
    "volume": 1888874
  },
  {
    "date": "04/01",
    "open": 1025.0,
    "high": 1063.0,
    "low": 1017.0,
    "close": 1043.0,
    "volume": 1428485
  },
  {
    "date": "04/02",
    "open": 1039.0,
    "high": 1070.0,
    "low": 1020.0,
    "close": 1056.0,
    "volume": 667562
  },
  {
    "date": "04/03",
    "open": 1052.0,
    "high": 1069.0,
    "low": 1031.0,
    "close": 1051.0,
    "volume": 943877
  },
  {
    "date": "04/04",
    "open": 1090.0,
    "high": 1111.0,
    "low": 1039.0,
    "close": 1054.0,
    "volume": 1676048
  },
  {
    "date": "04/07",
    "open": 1106.0,
    "high": 1127.0,
    "low": 1071.0,
    "close": 1080.0,
    "volume": 264077
  },
  {
    "date": "04/08",
    "open": 1089.0,
    "high": 1142.0,
    "low": 1068.0,
    "close": 1132.0,
    "volume": 1451656
  },
  {
    "date": "04/09",
    "open": 1057.0,
    "high": 1080.0,
    "low": 1040.0,
    "close": 1068.0,
    "volume": 563480
  },
  {
    "date": "04/10",
    "open": 1028.0,
    "high": 1071.0,
    "low": 1017.0,
    "close": 1060.0,
    "volume": 593485
  },
  {
    "date": "04/11",
    "open": 1065.0,
    "high": 1084.0,
    "low": 1023.0,
    "close": 1038.0,
    "volume": 1806697
  },
  {
    "date": "04/14",
    "open": 1094.0,
    "high": 1094.0,
    "low": 1059.0,
    "close": 1066.0,
    "volume": 1389122
  },
  {
    "date": "04/15",
    "open": 1098.0,
    "high": 1105.0,
    "low": 1075.0,
    "close": 1091.0,
    "volume": 1148983
  },
  {
    "date": "04/16",
    "open": 1098.0,
    "high": 1129.0,
    "low": 1091.0,
    "close": 1115.0,
    "volume": 728536
  },
  {
    "date": "04/17",
    "open": 1132.0,
    "high": 1155.0,
    "low": 1125.0,
    "close": 1143.0,
    "volume": 1747555
  },
  {
    "date": "04/18",
    "open": 1142.0,
    "high": 1164.0,
    "low": 1103.0,
    "close": 1120.0,
    "volume": 785470
  },
  {
    "date": "04/21",
    "open": 1136.0,
    "high": 1157.0,
    "low": 1102.0,
    "close": 1114.0,
    "volume": 837435
  },
  {
    "date": "04/22",
    "open": 1138.0,
    "high": 1141.0,
    "low": 1116.0,
    "close": 1138.0,
    "volume": 1623246
  },
  {
    "date": "04/23",
    "open": 1084.0,
    "high": 1092.0,
    "low": 1073.0,
    "close": 1080.0,
    "volume": 686930
  },
  {
    "date": "04/24",
    "open": 1092.0,
    "high": 1110.0,
    "low": 1073.0,
    "close": 1079.0,
    "volume": 975268
  },
  {
    "date": "04/25",
    "open": 1058.0,
    "high": 1065.0,
    "low": 1056.0,
    "close": 1063.0,
    "volume": 446307
  },
  {
    "date": "04/28",
    "open": 1076.0,
    "high": 1094.0,
    "low": 1027.0,
    "close": 1047.0,
    "volume": 1606746
  },
  {
    "date": "04/29",
    "open": 1044.0,
    "high": 1082.0,
    "low": 1043.0,
    "close": 1073.0,
    "volume": 1654014
  },
  {
    "date": "04/30",
    "open": 1082.0,
    "high": 1083.0,
    "low": 1055.0,
    "close": 1060.0,
    "volume": 859324
  },
  {
    "date": "05/01",
    "open": 1053.0,
    "high": 1081.0,
    "low": 1038.0,
    "close": 1067.0,
    "volume": 382577
  },
  {
    "date": "05/02",
    "open": 1064.0,
    "high": 1076.0,
    "low": 1048.0,
    "close": 1057.0,
    "volume": 1319015
  },
  {
    "date": "05/05",
    "open": 1025.0,
    "high": 1036.0,
    "low": 1020.0,
    "close": 1029.0,
    "volume": 463590
  },
  {
    "date": "05/06",
    "open": 1036.0,
    "high": 1041.0,
    "low": 1011.0,
    "close": 1031.0,
    "volume": 1191369
  },
  {
    "date": "05/07",
    "open": 1042.0,
    "high": 1084.0,
    "low": 1037.0,
    "close": 1079.0,
    "volume": 459523
  },
  {
    "date": "05/08",
    "open": 1045.0,
    "high": 1050.0,
    "low": 1022.0,
    "close": 1034.0,
    "volume": 1351121
  },
  {
    "date": "05/09",
    "open": 1049.0,
    "high": 1051.0,
    "low": 1015.0,
    "close": 1028.0,
    "volume": 1378973
  },
  {
    "date": "05/12",
    "open": 1035.0,
    "high": 1051.0,
    "low": 1020.0,
    "close": 1025.0,
    "volume": 542805
  },
  {
    "date": "05/13",
    "open": 1005.0,
    "high": 1038.0,
    "low": 1004.0,
    "close": 1026.0,
    "volume": 515482
  },
  {
    "date": "05/14",
    "open": 1008.0,
    "high": 1016.0,
    "low": 996.0,
    "close": 1000.0,
    "volume": 883269
  },
  {
    "date": "05/15",
    "open": 1039.0,
    "high": 1049.0,
    "low": 1009.0,
    "close": 1023.0,
    "volume": 147961
  },
  {
    "date": "05/16",
    "open": 1024.0,
    "high": 1062.0,
    "low": 1018.0,
    "close": 1048.0,
    "volume": 1706507
  },
  {
    "date": "05/19",
    "open": 1014.0,
    "high": 1018.0,
    "low": 1011.0,
    "close": 1015.0,
    "volume": 651594
  },
  {
    "date": "05/20",
    "open": 1018.0,
    "high": 1058.0,
    "low": 998.0,
    "close": 1044.0,
    "volume": 347388
  },
  {
    "date": "05/21",
    "open": 1000.0,
    "high": 1012.0,
    "low": 972.0,
    "close": 982.0,
    "volume": 697511
  },
  {
    "date": "05/22",
    "open": 1027.0,
    "high": 1049.0,
    "low": 1023.0,
    "close": 1032.0,
    "volume": 1679324
  },
  {
    "date": "05/23",
    "open": 1030.0,
    "high": 1046.0,
    "low": 1017.0,
    "close": 1030.0,
    "volume": 78445
  },
  {
    "date": "05/26",
    "open": 1035.0,
    "high": 1076.0,
    "low": 1015.0,
    "close": 1061.0,
    "volume": 1370669
  },
  {
    "date": "05/27",
    "open": 1068.0,
    "high": 1081.0,
    "low": 1035.0,
    "close": 1053.0,
    "volume": 446976
  },
  {
    "date": "05/28",
    "open": 1033.0,
    "high": 1046.0,
    "low": 1029.0,
    "close": 1044.0,
    "volume": 437037
  },
  {
    "date": "05/29",
    "open": 1031.0,
    "high": 1060.0,
    "low": 1015.0,
    "close": 1041.0,
    "volume": 1893648
  },
  {
    "date": "05/30",
    "open": 1012.0,
    "high": 1037.0,
    "low": 1003.0,
    "close": 1029.0,
    "volume": 1032942
  },
  {
    "date": "06/02",
    "open": 1044.0,
    "high": 1053.0,
    "low": 1033.0,
    "close": 1045.0,
    "volume": 1587037
  },
  {
    "date": "06/03",
    "open": 1075.0,
    "high": 1075.0,
    "low": 1060.0,
    "close": 1068.0,
    "volume": 973257
  },
  {
    "date": "06/04",
    "open": 1067.0,
    "high": 1084.0,
    "low": 1056.0,
    "close": 1075.0,
    "volume": 210265
  },
  {
    "date": "06/05",
    "open": 1044.0,
    "high": 1068.0,
    "low": 1037.0,
    "close": 1048.0,
    "volume": 627287
  },
  {
    "date": "06/06",
    "open": 1071.0,
    "high": 1076.0,
    "low": 1046.0,
    "close": 1056.0,
    "volume": 741280
  },
  {
    "date": "06/09",
    "open": 1035.0,
    "high": 1049.0,
    "low": 1021.0,
    "close": 1035.0,
    "volume": 1934100
  },
  {
    "date": "06/10",
    "open": 1063.0,
    "high": 1080.0,
    "low": 1060.0,
    "close": 1073.0,
    "volume": 794769
  },
  {
    "date": "06/11",
    "open": 1093.0,
    "high": 1109.0,
    "low": 1065.0,
    "close": 1083.0,
    "volume": 515722
  },
  {
    "date": "06/12",
    "open": 1102.0,
    "high": 1140.0,
    "low": 1088.0,
    "close": 1131.0,
    "volume": 1751645
  },
  {
    "date": "06/13",
    "open": 1122.0,
    "high": 1160.0,
    "low": 1109.0,
    "close": 1139.0,
    "volume": 1882955
  },
  {
    "date": "06/16",
    "open": 1132.0,
    "high": 1135.0,
    "low": 1100.0,
    "close": 1117.0,
    "volume": 1710250
  },
  {
    "date": "06/17",
    "open": 1120.0,
    "high": 1143.0,
    "low": 1111.0,
    "close": 1124.0,
    "volume": 1784050
  },
  {
    "date": "06/18",
    "open": 1104.0,
    "high": 1120.0,
    "low": 1086.0,
    "close": 1103.0,
    "volume": 1512186
  },
  {
    "date": "06/19",
    "open": 1168.0,
    "high": 1178.0,
    "low": 1109.0,
    "close": 1129.0,
    "volume": 364167
  },
  {
    "date": "06/20",
    "open": 1126.0,
    "high": 1161.0,
    "low": 1105.0,
    "close": 1138.0,
    "volume": 1924861
  },
  {
    "date": "06/23",
    "open": 1145.0,
    "high": 1147.0,
    "low": 1132.0,
    "close": 1137.0,
    "volume": 1793735
  },
  {
    "date": "06/24",
    "open": 1151.0,
    "high": 1158.0,
    "low": 1134.0,
    "close": 1153.0,
    "volume": 915012
  },
  {
    "date": "06/25",
    "open": 1160.0,
    "high": 1182.0,
    "low": 1111.0,
    "close": 1116.0,
    "volume": 985635
  },
  {
    "date": "06/26",
    "open": 1152.0,
    "high": 1159.0,
    "low": 1099.0,
    "close": 1118.0,
    "volume": 97285
  },
  {
    "date": "06/27",
    "open": 1143.0,
    "high": 1146.0,
    "low": 1135.0,
    "close": 1143.0,
    "volume": 1545395
  },
  {
    "date": "06/30",
    "open": 1169.0,
    "high": 1185.0,
    "low": 1159.0,
    "close": 1183.0,
    "volume": 1850993
  },
  {
    "date": "07/01",
    "open": 1172.0,
    "high": 1195.0,
    "low": 1151.0,
    "close": 1187.0,
    "volume": 1084380
  },
  {
    "date": "07/02",
    "open": 1208.0,
    "high": 1223.0,
    "low": 1157.0,
    "close": 1171.0,
    "volume": 371674
  },
  {
    "date": "07/03",
    "open": 1244.0,
    "high": 1252.0,
    "low": 1226.0,
    "close": 1229.0,
    "volume": 374735
  },
  {
    "date": "07/04",
    "open": 1260.0,
    "high": 1270.0,
    "low": 1234.0,
    "close": 1248.0,
    "volume": 1460113
  },
  {
    "date": "07/07",
    "open": 1221.0,
    "high": 1279.0,
    "low": 1220.0,
    "close": 1262.0,
    "volume": 960491
  },
  {
    "date": "07/08",
    "open": 1186.0,
    "high": 1216.0,
    "low": 1168.0,
    "close": 1210.0,
    "volume": 1226036
  },
  {
    "date": "07/09",
    "open": 1230.0,
    "high": 1250.0,
    "low": 1214.0,
    "close": 1238.0,
    "volume": 245750
  },
  {
    "date": "07/10",
    "open": 1240.0,
    "high": 1249.0,
    "low": 1208.0,
    "close": 1210.0,
    "volume": 1295139
  },
  {
    "date": "07/11",
    "open": 1241.0,
    "high": 1300.0,
    "low": 1221.0,
    "close": 1276.0,
    "volume": 1217877
  },
  {
    "date": "07/14",
    "open": 1288.0,
    "high": 1313.0,
    "low": 1264.0,
    "close": 1309.0,
    "volume": 771589
  },
  {
    "date": "07/15",
    "open": 1293.0,
    "high": 1353.0,
    "low": 1292.0,
    "close": 1329.0,
    "volume": 925311
  },
  {
    "date": "07/16",
    "open": 1272.0,
    "high": 1283.0,
    "low": 1256.0,
    "close": 1276.0,
    "volume": 484443
  },
  {
    "date": "07/17",
    "open": 1253.0,
    "high": 1288.0,
    "low": 1236.0,
    "close": 1278.0,
    "volume": 351595
  },
  {
    "date": "07/18",
    "open": 1218.0,
    "high": 1240.0,
    "low": 1195.0,
    "close": 1223.0,
    "volume": 1760042
  },
  {
    "date": "07/21",
    "open": 1262.0,
    "high": 1273.0,
    "low": 1261.0,
    "close": 1272.0,
    "volume": 612857
  },
  {
    "date": "07/22",
    "open": 1299.0,
    "high": 1340.0,
    "low": 1279.0,
    "close": 1320.0,
    "volume": 961036
  },
  {
    "date": "07/23",
    "open": 1297.0,
    "high": 1298.0,
    "low": 1242.0,
    "close": 1258.0,
    "volume": 1435648
  },
  {
    "date": "07/24",
    "open": 1248.0,
    "high": 1273.0,
    "low": 1240.0,
    "close": 1250.0,
    "volume": 1859924
  },
  {
    "date": "07/25",
    "open": 1300.0,
    "high": 1315.0,
    "low": 1271.0,
    "close": 1289.0,
    "volume": 946004
  },
  {
    "date": "07/28",
    "open": 1285.0,
    "high": 1328.0,
    "low": 1264.0,
    "close": 1327.0,
    "volume": 696296
  },
  {
    "date": "07/29",
    "open": 1266.0,
    "high": 1322.0,
    "low": 1261.0,
    "close": 1303.0,
    "volume": 1320647
  },
  {
    "date": "07/30",
    "open": 1298.0,
    "high": 1326.0,
    "low": 1279.0,
    "close": 1313.0,
    "volume": 52716
  },
  {
    "date": "07/31",
    "open": 1309.0,
    "high": 1310.0,
    "low": 1286.0,
    "close": 1298.0,
    "volume": 213596
  },
  {
    "date": "08/01",
    "open": 1317.0,
    "high": 1335.0,
    "low": 1294.0,
    "close": 1325.0,
    "volume": 1495540
  },
  {
    "date": "08/04",
    "open": 1320.0,
    "high": 1374.0,
    "low": 1314.0,
    "close": 1351.0,
    "volume": 1702495
  },
  {
    "date": "08/05",
    "open": 1368.0,
    "high": 1385.0,
    "low": 1363.0,
    "close": 1380.0,
    "volume": 1094271
  },
  {
    "date": "08/06",
    "open": 1379.0,
    "high": 1392.0,
    "low": 1347.0,
    "close": 1369.0,
    "volume": 1708608
  },
  {
    "date": "08/07",
    "open": 1350.0,
    "high": 1377.0,
    "low": 1344.0,
    "close": 1360.0,
    "volume": 1359440
  },
  {
    "date": "08/08",
    "open": 1399.0,
    "high": 1425.0,
    "low": 1386.0,
    "close": 1397.0,
    "volume": 830732
  },
  {
    "date": "08/11",
    "open": 1417.0,
    "high": 1418.0,
    "low": 1402.0,
    "close": 1405.0,
    "volume": 475737
  },
  {
    "date": "08/12",
    "open": 1411.0,
    "high": 1437.0,
    "low": 1400.0,
    "close": 1416.0,
    "volume": 1472396
  },
  {
    "date": "08/13",
    "open": 1366.0,
    "high": 1395.0,
    "low": 1350.0,
    "close": 1395.0,
    "volume": 643256
  },
  {
    "date": "08/14",
    "open": 1409.0,
    "high": 1463.0,
    "low": 1382.0,
    "close": 1434.0,
    "volume": 1420737
  },
  {
    "date": "08/15",
    "open": 1364.0,
    "high": 1376.0,
    "low": 1351.0,
    "close": 1363.0,
    "volume": 388911
  },
  {
    "date": "08/18",
    "open": 1368.0,
    "high": 1416.0,
    "low": 1354.0,
    "close": 1396.0,
    "volume": 1905103
  },
  {
    "date": "08/19",
    "open": 1374.0,
    "high": 1412.0,
    "low": 1358.0,
    "close": 1397.0,
    "volume": 1725842
  },
  {
    "date": "08/20",
    "open": 1389.0,
    "high": 1397.0,
    "low": 1375.0,
    "close": 1388.0,
    "volume": 530411
  },
  {
    "date": "08/21",
    "open": 1413.0,
    "high": 1424.0,
    "low": 1394.0,
    "close": 1415.0,
    "volume": 1979745
  },
  {
    "date": "08/22",
    "open": 1400.0,
    "high": 1418.0,
    "low": 1376.0,
    "close": 1398.0,
    "volume": 1646237
  },
  {
    "date": "08/25",
    "open": 1388.0,
    "high": 1440.0,
    "low": 1381.0,
    "close": 1432.0,
    "volume": 1188312
  },
  {
    "date": "08/26",
    "open": 1362.0,
    "high": 1411.0,
    "low": 1357.0,
    "close": 1394.0,
    "volume": 605019
  },
  {
    "date": "08/27",
    "open": 1403.0,
    "high": 1429.0,
    "low": 1388.0,
    "close": 1416.0,
    "volume": 1063792
  },
  {
    "date": "08/28",
    "open": 1369.0,
    "high": 1389.0,
    "low": 1353.0,
    "close": 1385.0,
    "volume": 166856
  },
  {
    "date": "08/29",
    "open": 1398.0,
    "high": 1405.0,
    "low": 1356.0,
    "close": 1360.0,
    "volume": 745014
  },
  {
    "date": "09/01",
    "open": 1417.0,
    "high": 1419.0,
    "low": 1387.0,
    "close": 1396.0,
    "volume": 1655455
  },
  {
    "date": "09/02",
    "open": 1395.0,
    "high": 1430.0,
    "low": 1388.0,
    "close": 1426.0,
    "volume": 488960
  },
  {
    "date": "09/03",
    "open": 1456.0,
    "high": 1475.0,
    "low": 1427.0,
    "close": 1430.0,
    "volume": 1709799
  },
  {
    "date": "09/04",
    "open": 1423.0,
    "high": 1484.0,
    "low": 1410.0,
    "close": 1476.0,
    "volume": 1417796
  },
  {
    "date": "09/05",
    "open": 1463.0,
    "high": 1473.0,
    "low": 1454.0,
    "close": 1460.0,
    "volume": 1706319
  },
  {
    "date": "09/08",
    "open": 1471.0,
    "high": 1483.0,
    "low": 1408.0,
    "close": 1436.0,
    "volume": 699637
  },
  {
    "date": "09/09",
    "open": 1490.0,
    "high": 1507.0,
    "low": 1488.0,
    "close": 1503.0,
    "volume": 1690509
  },
  {
    "date": "09/10",
    "open": 1483.0,
    "high": 1494.0,
    "low": 1462.0,
    "close": 1481.0,
    "volume": 1349869
  },
  {
    "date": "09/11",
    "open": 1454.0,
    "high": 1464.0,
    "low": 1453.0,
    "close": 1458.0,
    "volume": 1254225
  },
  {
    "date": "09/12",
    "open": 1416.0,
    "high": 1427.0,
    "low": 1410.0,
    "close": 1419.0,
    "volume": 1609944
  },
  {
    "date": "09/15",
    "open": 1455.0,
    "high": 1459.0,
    "low": 1417.0,
    "close": 1434.0,
    "volume": 550349
  },
  {
    "date": "09/16",
    "open": 1424.0,
    "high": 1447.0,
    "low": 1421.0,
    "close": 1439.0,
    "volume": 360046
  },
  {
    "date": "09/17",
    "open": 1498.0,
    "high": 1518.0,
    "low": 1449.0,
    "close": 1476.0,
    "volume": 59546
  },
  {
    "date": "09/18",
    "open": 1520.0,
    "high": 1527.0,
    "low": 1472.0,
    "close": 1483.0,
    "volume": 1538452
  },
  {
    "date": "09/19",
    "open": 1482.0,
    "high": 1526.0,
    "low": 1457.0,
    "close": 1513.0,
    "volume": 607292
  },
  {
    "date": "09/22",
    "open": 1447.0,
    "high": 1500.0,
    "low": 1421.0,
    "close": 1486.0,
    "volume": 1785458
  },
  {
    "date": "09/23",
    "open": 1503.0,
    "high": 1522.0,
    "low": 1446.0,
    "close": 1475.0,
    "volume": 682880
  },
  {
    "date": "09/24",
    "open": 1506.0,
    "high": 1536.0,
    "low": 1465.0,
    "close": 1494.0,
    "volume": 1434297
  }
]